pyVIA/__init__.py
pyVIA/core.py
pyVIA/datasets_via.py
pyVIA/examples.py
pyVIA/plotting_via.py
pyVIA/utils_via.py
pyVIA/windmap.py
pyVIA-0.2.4.dist-info/METADATA
pyVIA-0.2.4.dist-info/WHEEL
pyVIA-0.2.4.dist-info/top_level.txt
pyVIA-0.2.4.dist-info/RECORD
