Metadata-Version: 2.1
Name: pyVIA
Version: 0.2.4
Home-page: https://github.com/ShobiStassen/VIA
Author-email: shobana.venkat88@gmail.com
License: MIT
Requires-Python: >=3.8
Requires-Dist: pybind11
Requires-Dist: numpy>=1.17
Requires-Dist: scipy
Requires-Dist: pandas>=0.25
Requires-Dist: hnswlib
Requires-Dist: igraph
Requires-Dist: leidenalg>=0.7.0
Requires-Dist: scikit-learn
Requires-Dist: termcolor
Requires-Dist: pygam
Requires-Dist: matplotlib
Requires-Dist: scanpy
Requires-Dist: umap-learn>=0.5.0
Requires-Dist: phate
Requires-Dist: datashader
Requires-Dist: scikit-image
Requires-Dist: pillow
Requires-Dist: wget
Requires-Dist: gdown
Requires-Dist: seaborn
Requires-Dist: pecanpy
Requires-Dist: holoviews
